pokit/stack/__init__.py
pokit/stack/app.py
pokit/stack/types/__init__.py
pokit/stack/types/asgi.py
pokit/stack/types/handler.py
pokit/stack/types/http.py
pokit_stack-0.0.0a4.dist-info/METADATA
pokit_stack-0.0.0a4.dist-info/WHEEL
pokit_stack-0.0.0a4.dist-info/RECORD
