Metadata-Version: 2.4
Name: pokit-stack
Version: 0.0.0a4
Summary: Lightweight ASGI framework for building JSON APIs.
Requires-Python: <4.0,>=3.12
Requires-Dist: msgspec<1.0.0,>=0.20.0
Requires-Dist: uvicorn<1.0.0,>=0.40.0
